candyman1/CandyMan.py
candyman1/__init__.py
CandyMan1-0.0.5.dist-info/LICENSE
CandyMan1-0.0.5.dist-info/METADATA
CandyMan1-0.0.5.dist-info/WHEEL
CandyMan1-0.0.5.dist-info/top_level.txt
CandyMan1-0.0.5.dist-info/RECORD
