Metadata-Version: 2.1
Name: CandyMan1
Version: 0.0.5
Summary: A package for astronomy stuffs
Home-page: https://github.com/backyard-Py/candyman
Author: himangshu147-git
Author-email: himangshu147@invail.mail
License: BSD 2-clause
Classifier: Development Status :: 4 - Beta
Classifier: Intended Audience :: Science/Research
Classifier: License :: OSI Approved :: MIT License
Classifier: Operating System :: OS Independent
Classifier: Programming Language :: Python :: 3.10
License-File: LICENSE
Requires-Dist: requests
